__init__.py
pyPrairieView/__init__.py
pyPrairieView/bruker_meta_objects.py
pyPrairieView/bruker_xml_objects.py
pyPrairieView/configuration_values.py
pyPrairieView/data_sync.py
pyPrairieView/ephys_analyzer.py
pyPrairieView/generate_stimulus.py
pyPrairieView/io_tools.py
pyPrairieView/mark_points.py
pyPrairieView/microscope_properties.py
pyPrairieView/package_info.py
pyPrairieView/prairieview_xml.py
pyPrairieView/validation.py
pyPrairieView/xml_load.py
pyPrairieView/dev/generate_basic_protocol.py
pyPrairieView/dev/generate_biphasic.py
pyPrairieView/dev/generate_chirp_stimulus.py
pyPrairieView/dev/generate_epoch.py
pyPrairieView/dev/generate_iv_curve.py
pyPrairieView/dev/generate_non-linear_chirp.py
pyPrairieView/dev/generate_one-sided_voltage_ramp.py
pyPrairieView/dev/generate_prairieview_stimulus.py
pyPrairieView/dev/generate_prairieview_waveform.py
pyPrairieView/dev/generate_repeat.py
pyPrairieView/dev/generate_tail_currents.py
pyPrairieView/dev/generate_voltage_ramp.py
pyPrairieView/dev/generate_voltage_steps.py
pyPrairieView/xml_mappings/__init__.py
pyPrairieView/xml_mappings/xml_mapping.py
pyPrairieView-0.0.2.dist-info/LICENSE
pyPrairieView-0.0.2.dist-info/METADATA
pyPrairieView-0.0.2.dist-info/WHEEL
pyPrairieView-0.0.2.dist-info/top_level.txt
pyPrairieView-0.0.2.dist-info/RECORD
