Metadata-Version: 2.1
Name: pyPrairieView
Version: 0.0.2
Summary: Darik & Doug Do A Thing
Author: Douglas Miller, Darik A. O'Neil
Maintainer: Douglas Miller, Darik A. O'Neil
License: MIT License
Project-URL: documentation, https://github.com/saglag/pyPrairieView
Project-URL: repository, https://github.com/saglag/pyPrairieView
Keywords: Bruker,PrairieView,Microscopy,Two-Photon,One-Photon,Confocal,Electrophysiology,Ephys,Neuroscience,Psychology,Biology
Classifier: Development Status :: 3 - Alpha
Classifier: Programming Language :: Python
Classifier: Operating System :: Microsoft :: Windows
Classifier: Operating System :: POSIX
Classifier: Operating System :: Unix
Classifier: Programming Language :: Python :: 3.7
Classifier: Programming Language :: Python :: 3.8
Classifier: Programming Language :: Python :: 3.9
Classifier: Programming Language :: Python :: 3.10
Classifier: Natural Language :: English
Classifier: License :: OSI Approved :: MIT License
Classifier: Intended Audience :: Science/Research
Classifier: Intended Audience :: End Users/Desktop
Classifier: Topic :: Scientific/Engineering
Requires-Python: <4,>=3.7
License-File: LICENSE
Requires-Dist: numpy
Requires-Dist: pandas
Requires-Dist: pillow
Requires-Dist: PPVD
Requires-Dist: prettytable
Requires-Dist: tifffile
Requires-Dist: tqdm
Provides-Extra: development
Requires-Dist: build ; extra == 'development'
Requires-Dist: coverage[toml] ; extra == 'development'
Requires-Dist: coveralls ; extra == 'development'
Requires-Dist: flake8 ; extra == 'development'
Requires-Dist: flake8-annotations ; extra == 'development'
Requires-Dist: flake8-bugbear ; extra == 'development'
Requires-Dist: flake8-class-attributes-order ; extra == 'development'
Requires-Dist: flake8-comprehensions ; extra == 'development'
Requires-Dist: flake8-html ; extra == 'development'
Requires-Dist: flake8-unused-arguments ; extra == 'development'
Requires-Dist: toml ; extra == 'development'
Requires-Dist: tomli ; extra == 'development'
Requires-Dist: twine ; extra == 'development'
Provides-Extra: documentation
Requires-Dist: sphinx ; extra == 'documentation'
Requires-Dist: sphinx-rtd-theme ; extra == 'documentation'
Requires-Dist: sphinx-autodoc-typehints ; extra == 'documentation'
Provides-Extra: tests
Requires-Dist: pytest ; extra == 'tests'
Requires-Dist: pytest-datafiles ; extra == 'tests'
Requires-Dist: pytest-lazy-fixture ; extra == 'tests'
Requires-Dist: pytest-sugar ; extra == 'tests'
Requires-Dist: pytest-clarity ; extra == 'tests'
